{"paths":{},"types":[],"uuids":["07iHtQzPRJq6TkOXp9msPJ","0dpZm8L8RJXpaUvBFdl0zF","1bH9rPVrlMh7f6RYuYpukc","23bpiLQTdHq703mY6hkSjh","2aw6qYEgVPSLgB7Fb0DeL5","39a70UWOZC/6jGz9Q1NTVt","3bMjn49xxBC66CfJla2ARv","3eANLd6HdMa5Fo54YF7xP7","71VhFCTINJM6/Ky3oX9nBT","74m5d8vdBDh5FRZpc0JwSx","7bPsaW6kZD2qpWpRYLPUro","85y/ZhzGVGFpmloatWDTvM","88inGecEVPf54GnTAHZFMe","89hbfedIxBDYvP/CzuoJOi","afL6JmFcVDyqPo8Df8LZ1v","b4P/PCArtIdIH38t6mlw8Y","c1nWHe64FFsIiS2HwIXOMJ","cdZf05kRlHdKpmEt+qmrr7","d5rFYH7aVKKJtYm9SERYxI","ddc7v2wn9P+4ljZI3hPmN3","e0kVcSQqlGv7Ui2GTse4AI","e8Ueib+qJEhL6mXAHdnwbi","02delMVqdBD70a/HSD99FK","073tZSSQJFqIiSIkeJPT0O","0bdz7zle9EC5wah+MOsxGM","1fWQMNdNJPFIet5L/Fwy0R","29FYIk+N1GYaeWH/q1NxQO","3469fM4PtPx4pKL5cDWQl3","3cjEIVhjFHG6rvcV4J3gNf","83CPb+FsxEXIX4cOeKQCgH","8847wUxNBOPb4IN+fb/Cu6","93sJPZeLVJ5ZX7fnLIhrtk","a2MjXRFdtLlYQ5ouAFv/+R","a4zmSM38JD15jdmeTuODhH","b8FVD5XFxLzJpwX0u+gTYl","bdZn+jHnZBsa6S0JYGzAT7","d2M8VjLQJLXpoIgYWHMIO1","e97GVMl6JHh5Ml5qEDdSGa","ecpdLyjvZBwrvm+cedCcQy","f0BIwQ8D5Ml7nTNQbh1YlS","fcMnLnbMBKJaRvyeekIvT7"],"scenes":{"db://assets/scene.fire":18},"redirect":[22,0,38,0],"deps":["internal"],"packs":{"011ab6699":[0,23,24,1,2,25,3,26,4,27,5,6,28,7,8,9,10,29,11,12,30,13,31,32,33,14,15,34,35,16,17,36,18,19,20,21,37,39,40]},"name":"main","importBase":"import","nativeBase":"native","debug":false,"isZip":false,"encrypted":false,"versions":{"import":["011ab6699","d0d65"],"native":[0,"be79b",1,"9ab11",2,"1e029",3,"1822c",4,"ac4e5",5,"24f0f",6,"216dc",7,"c892d",8,"0c6ef",9,"30f91",10,"45a81",11,"7dd51",12,"2bf97",13,"e2b1f",14,"9db62",15,"11e66",16,"6f9bd",17,"fc30c",19,"ea4cc",20,"0f55b",21,"cc83c"]}}